fwd_sdk/__init__.py
fwd_sdk/api_client.py
fwd_sdk/api_response.py
fwd_sdk/configuration.py
fwd_sdk/exceptions.py
fwd_sdk/py.typed
fwd_sdk/rest.py
fwd_sdk/api/__init__.py
fwd_sdk/api/audio_api.py
fwd_sdk/api/chat_api.py
fwd_sdk/api/compute_api.py
fwd_sdk/api/embeddings_api.py
fwd_sdk/api/images_api.py
fwd_sdk/api/instances_api.py
fwd_sdk/api/models_api.py
fwd_sdk/api/ssh_keys_api.py
fwd_sdk/api/support_api.py
fwd_sdk/api/volumes_api.py
fwd_sdk/models/__init__.py
fwd_sdk/models/audio_create_speech_post200_response.py
fwd_sdk/models/audio_create_speech_post400_response.py
fwd_sdk/models/audio_create_speech_post400_response_error.py
fwd_sdk/models/audio_create_speech_post402_response.py
fwd_sdk/models/audio_create_speech_post402_response_error.py
fwd_sdk/models/audio_create_speech_post_request.py
fwd_sdk/models/audio_create_transcription_post200_response.py
fwd_sdk/models/audio_create_transcription_post200_response_segments_inner.py
fwd_sdk/models/audio_create_transcription_post_request.py
fwd_sdk/models/audio_create_translation_post_request.py
fwd_sdk/models/audio_list_voices_get200_response.py
fwd_sdk/models/audio_list_voices_get200_response_voices_inner.py
fwd_sdk/models/chat_create_completion_post200_response.py
fwd_sdk/models/chat_create_completion_post200_response_choices_inner.py
fwd_sdk/models/chat_create_completion_post200_response_usage.py
fwd_sdk/models/chat_create_completion_post402_response.py
fwd_sdk/models/chat_create_completion_post402_response_error.py
fwd_sdk/models/chat_create_completion_post_request.py
fwd_sdk/models/chat_create_completion_post_request_messages_inner.py
fwd_sdk/models/chat_create_completion_post_request_messages_inner_tool_calls_inner.py
fwd_sdk/models/chat_create_completion_post_request_messages_inner_tool_calls_inner_function.py
fwd_sdk/models/chat_create_completion_post_request_tools_inner.py
fwd_sdk/models/chat_create_completion_post_request_tools_inner_function.py
fwd_sdk/models/chat_list_completions_get200_response.py
fwd_sdk-0.1.1.dist-info/METADATA
fwd_sdk-0.1.1.dist-info/WHEEL
fwd_sdk-0.1.1.dist-info/top_level.txt
fwd_sdk-0.1.1.dist-info/RECORD
