Metadata-Version: 2.4
Name: fwd_sdk
Version: 0.1.1
Summary: Forward Compute API
Home-page: https://github.com/forwardcompute/python-sdk
Author: Forward Compute API
Author-email: Forward Compute API <team@openapitools.org>
Project-URL: Repository, https://github.com/GIT_USER_ID/GIT_REPO_ID
Keywords: OpenAPI,OpenAPI-Generator,Forward Compute API
Requires-Python: >=3.9
Requires-Dist: urllib3<3.0.0,>=2.1.0
Requires-Dist: python-dateutil>=2.8.2
Requires-Dist: pydantic>=2
Requires-Dist: typing-extensions>=4.7.1
Dynamic: author
Dynamic: home-page
